a3mtools/__init__.py
a3mtools/examples.py
a3mtools/backend/__init__.py
a3mtools/backend/a3m_tools.py
a3mtools/backend/fasta_tools.py
a3mtools/backend/sequence_utils.py
a3mtools/test_data/__init__.py
a3mtools/test_data/test_msa_1.a3m
a3mtools/test_data/test_msa_2.a3m
a3mtools/test_data/test_msa_3.fasta
a3mtools/tests/__init__.py
a3mtools/tests/test_a3mtools.py
a3mtools-0.1.0a6.dist-info/licenses/LICENSE
a3mtools-0.1.0a6.dist-info/WHEEL
a3mtools-0.1.0a6.dist-info/METADATA
a3mtools-0.1.0a6.dist-info/RECORD
