Metadata-Version: 2.4
Name: a3mtools
Version: 0.1.0a6
Summary: tools for working with a3m files for structure prediction
Author: Jackson Halpin
Requires-Python: ~=3.10
Classifier: Programming Language :: Python :: 3
Classifier: License :: OSI Approved :: MIT License
License-File: LICENSE
Requires-Dist: importlib-resources
Requires-Dist: numpy<2
Requires-Dist: biopython >= 1.8
Requires-Dist: a3mcat
Requires-Dist: mkdocs ; extra == "doc"
Requires-Dist: pytest>=6.1.2 ; extra == "test"
Project-URL: Source, https://github.com/jacksonh1/a3mtools
Provides-Extra: doc
Provides-Extra: test
